pydatamodel/__init__.py
pydatamodel/creditScore.py
pydatamodel/dataAnalysis.py
pydatamodel/databaseModel.py
pydatamodel/mechineLearning.py
pydatamodel-0.1.5.dist-info/LICENSE
pydatamodel-0.1.5.dist-info/METADATA
pydatamodel-0.1.5.dist-info/WHEEL
pydatamodel-0.1.5.dist-info/entry_points.txt
pydatamodel-0.1.5.dist-info/top_level.txt
pydatamodel-0.1.5.dist-info/RECORD
