Metadata-Version: 2.1
Name: pydatamodel
Version: 0.1.5
Summary: creditScore,dataAnalysis,databaseModel,mechineLearning
Home-page: https://pypi.python.org/pypi?%3Aaction=list_classifiers
Author: xuguanming
Author-email: xgm9981@163.com
License: MIT
Classifier: License :: OSI Approved :: MIT License
Classifier: Programming Language :: Python
Classifier: Programming Language :: Python :: 3
Requires-Python: >=3
License-File: LICENSE
Requires-Dist: numpy
Requires-Dist: pandas
Requires-Dist: matplotlib
Requires-Dist: statsmodels
Requires-Dist: scikit-learn
Requires-Dist: openpyxl
